ComputerNetworksASystemsApproach5thEd/README.md
ComputerNetworksASystemsApproach5thEd/__init__.py
ComputerNetworksASystemsApproach5thEd/__main__.py
ComputerNetworksASystemsApproach5thEd/file.epub
ComputerNetworksASystemsApproach5thEd/index.html
ComputerNetworksASystemsApproach5thEd/css/__init__.py
ComputerNetworksASystemsApproach5thEd/css/annotations.css
ComputerNetworksASystemsApproach5thEd/css/main.css
ComputerNetworksASystemsApproach5thEd/css/normalize.css
ComputerNetworksASystemsApproach5thEd/css/popup.css
ComputerNetworksASystemsApproach5thEd/font/__init__.py
ComputerNetworksASystemsApproach5thEd/font/fontello.eot
ComputerNetworksASystemsApproach5thEd/font/fontello.svg
ComputerNetworksASystemsApproach5thEd/font/fontello.ttf
ComputerNetworksASystemsApproach5thEd/font/fontello.woff
ComputerNetworksASystemsApproach5thEd/img/__init__.py
ComputerNetworksASystemsApproach5thEd/img/annotator-glyph-sprite.png
ComputerNetworksASystemsApproach5thEd/img/annotator-icon-sprite.png
ComputerNetworksASystemsApproach5thEd/img/apple-touch-icon.png
ComputerNetworksASystemsApproach5thEd/img/cancelfullscreen.png
ComputerNetworksASystemsApproach5thEd/img/close.png
ComputerNetworksASystemsApproach5thEd/img/fullscreen.png
ComputerNetworksASystemsApproach5thEd/img/loader.gif
ComputerNetworksASystemsApproach5thEd/img/menu-icon.png
ComputerNetworksASystemsApproach5thEd/img/save.png
ComputerNetworksASystemsApproach5thEd/img/saved.png
ComputerNetworksASystemsApproach5thEd/img/settings-s.png
ComputerNetworksASystemsApproach5thEd/img/settings.png
ComputerNetworksASystemsApproach5thEd/img/star.png
ComputerNetworksASystemsApproach5thEd/js/__init__.py
ComputerNetworksASystemsApproach5thEd/js/epub.js
ComputerNetworksASystemsApproach5thEd/js/epub.min.js
ComputerNetworksASystemsApproach5thEd/js/epub.min.map
ComputerNetworksASystemsApproach5thEd/js/hooks.min.js
ComputerNetworksASystemsApproach5thEd/js/hooks.min.map
ComputerNetworksASystemsApproach5thEd/js/reader.js
computer_networks_a_systems_approach_5th_ed-2024.3.3.0.dist-info/METADATA
computer_networks_a_systems_approach_5th_ed-2024.3.3.0.dist-info/WHEEL
computer_networks_a_systems_approach_5th_ed-2024.3.3.0.dist-info/entry_points.txt
computer_networks_a_systems_approach_5th_ed-2024.3.3.0.dist-info/top_level.txt
computer_networks_a_systems_approach_5th_ed-2024.3.3.0.dist-info/RECORD
